byu_jwt/__init__.py
byu_jwt/exceptions.py
byu_jwt-2.1.0.dist-info/LICENSE
byu_jwt-2.1.0.dist-info/METADATA
byu_jwt-2.1.0.dist-info/WHEEL
byu_jwt-2.1.0.dist-info/RECORD
