Metadata-Version: 2.3
Name: byu_jwt
Version: 2.1.0
Summary: 
License: Apache-2.0
Author: Application Engineering
Author-email: oit-developer@byu.edu
Requires-Python: >=3.9,<4.0
Classifier: License :: OSI Approved :: Apache Software License
Classifier: Programming Language :: Python :: 3
Classifier: Programming Language :: Python :: 3.9
Classifier: Programming Language :: Python :: 3.10
Classifier: Programming Language :: Python :: 3.11
Classifier: Programming Language :: Python :: 3.12
Classifier: Programming Language :: Python :: 3.13
Requires-Dist: cryptography (>=3)
Requires-Dist: pyjwt (>=2.10,<3.0)
Requires-Dist: requests (>=2.32,<3.0)
Project-URL: Homepage, https://github.com/byu-oit/byu-jwt-python
Project-URL: Repository, https://github.com/byu-oit/byu-jwt-python
